setup.py
JSTMB_FeatureSelection_primitive/JSTMBFeatSelector.py
JSTMB_FeatureSelection_primitive/JSTMB_FeatureSelection_primitive.ctf
JSTMB_FeatureSelection_primitive/__init__.py
JSTMB_FeatureSelection_primitive/base.py
JSTMB_FeatureSelection_primitive/supervised_learning.py
JSTMB_FeatureSelection_primitive.egg-info/PKG-INFO
JSTMB_FeatureSelection_primitive.egg-info/SOURCES.txt
JSTMB_FeatureSelection_primitive.egg-info/dependency_links.txt
JSTMB_FeatureSelection_primitive.egg-info/top_level.txt